haystack_redis.py
haystack_redis-0.0.1.dist-info/LICENSE
haystack_redis-0.0.1.dist-info/METADATA
haystack_redis-0.0.1.dist-info/WHEEL
haystack_redis-0.0.1.dist-info/top_level.txt
haystack_redis-0.0.1.dist-info/RECORD
