Metadata-Version: 2.1
Name: haystack-redis
Version: 0.0.1
Summary: Use redis as a persistence layer for Whoosh and Haystack
Home-page: https://github.com/steinbro/haystack-redis
Author: Jökull Sólberg Auðunsson
Author-email: jokull@solberg.is
Maintainer: Daniel W. Steinbrook
Maintainer-email: steinbro@post.harvard.edu
License: BSD
Platform: any
Classifier: Environment :: Web Environment
Classifier: Intended Audience :: Developers
Classifier: License :: OSI Approved :: BSD License
Classifier: Operating System :: OS Independent
Classifier: Programming Language :: Python
Classifier: Topic :: Internet :: WWW/HTTP :: Dynamic Content
Classifier: Topic :: Software Development :: Libraries :: Python Modules
Requires-Dist: django-haystack
Requires-Dist: redis
Requires-Dist: whoosh
